{
  "product": "Second Brain Agentic Platform",
  "version": "1.0.0",
  "created": "2024",
  "description": "Epics and User Stories for transforming Second Brain into an agentic productivity platform",
  "phases": [
    {
      "id": "phase-0",
      "name": "Foundation & UX - Responsive Layout",
      "weeks": "1-3",
      "epics": ["EPIC-020"]
    },
    {
      "id": "phase-1",
      "name": "Foundation - Enhanced Intelligence Layer",
      "weeks": "1-4",
      "epics": ["EPIC-001", "EPIC-002", "EPIC-003"]
    },
    {
      "id": "phase-2",
      "name": "Proactive Intelligence",
      "weeks": "5-8",
      "epics": ["EPIC-004", "EPIC-005", "EPIC-006"]
    },
    {
      "id": "phase-3",
      "name": "Action Execution Layer",
      "weeks": "9-12",
      "epics": ["EPIC-007", "EPIC-008", "EPIC-009"]
    },
    {
      "id": "phase-4",
      "name": "External Integrations",
      "weeks": "13-16",
      "epics": ["EPIC-010", "EPIC-011", "EPIC-012", "EPIC-013"]
    },
    {
      "id": "phase-5",
      "name": "Advanced Agentic Features",
      "weeks": "17-20",
      "epics": ["EPIC-014", "EPIC-015", "EPIC-016"]
    },
    {
      "id": "phase-6",
      "name": "Mobile & Capture Enhancements",
      "weeks": "21-24",
      "epics": ["EPIC-017", "EPIC-018", "EPIC-019"]
    }
  ],
  "priorityLevels": {
    "P0": "Critical - Blocks other work or core functionality",
    "P1": "High - Major feature, significant user value",
    "P2": "Medium - Important enhancement",
    "P3": "Low - Nice to have, can be deferred"
  },
  "storyPointScale": {
    "1": "Trivial (< 1 day)",
    "2": "Small (1-2 days)",
    "3": "Medium (3-5 days)",
    "5": "Large (1-2 weeks)",
    "8": "Very Large (2-3 weeks)",
    "13": "Epic (3+ weeks)"
  },
  "epics": [
    {
      "id": "EPIC-001",
      "name": "Natural Language Query Engine",
      "phase": "phase-1",
      "priority": "P1",
      "timeline": "Weeks 1-2",
      "storyPoints": 34,
      "file": "epics/EPIC-001-natural-language-query-engine.md"
    },
    {
      "id": "EPIC-002",
      "name": "Relationship Graph Engine",
      "phase": "phase-1",
      "priority": "P1",
      "timeline": "Weeks 2-3",
      "storyPoints": 29,
      "file": "epics/EPIC-002-relationship-graph-engine.md"
    },
    {
      "id": "EPIC-003",
      "name": "Enhanced Learning System",
      "phase": "phase-1",
      "priority": "P1",
      "timeline": "Weeks 3-4",
      "storyPoints": 21,
      "file": "epics/EPIC-003-enhanced-learning-system.md"
    },
    {
      "id": "EPIC-004",
      "name": "Smart Reminders & Notifications",
      "phase": "phase-2",
      "priority": "P1",
      "timeline": "Weeks 5-6",
      "storyPoints": 26,
      "file": "epics/EPIC-004-smart-reminders-notifications.md"
    },
    {
      "id": "EPIC-005",
      "name": "Proactive Insights Engine",
      "phase": "phase-2",
      "priority": "P1",
      "timeline": "Weeks 6-7",
      "storyPoints": 21,
      "file": "epics/EPIC-005-proactive-insights-engine.md"
    },
    {
      "id": "EPIC-006",
      "name": "Goal Tracking & OKRs",
      "phase": "phase-2",
      "priority": "P1",
      "timeline": "Weeks 7-8",
      "storyPoints": 26,
      "file": "epics/EPIC-006-goal-tracking-okrs.md"
    },
    {
      "id": "EPIC-007",
      "name": "Action Framework",
      "phase": "phase-3",
      "priority": "P1",
      "timeline": "Weeks 9-10",
      "storyPoints": 34,
      "file": "epics/EPIC-007-action-framework.md"
    },
    {
      "id": "EPIC-008",
      "name": "Workflow Automation Engine",
      "phase": "phase-3",
      "priority": "P1",
      "timeline": "Weeks 10-11",
      "storyPoints": 34,
      "file": "epics/EPIC-008-workflow-automation-engine.md"
    },
    {
      "id": "EPIC-009",
      "name": "Multi-Step Action Planner",
      "phase": "phase-3",
      "priority": "P1",
      "timeline": "Weeks 11-12",
      "storyPoints": 26,
      "file": "epics/EPIC-009-multi-step-action-planner.md"
    },
    {
      "id": "EPIC-010",
      "name": "Integration Framework",
      "phase": "phase-4",
      "priority": "P1",
      "timeline": "Week 13",
      "storyPoints": 21,
      "file": "epics/EPIC-010-integration-framework.md"
    },
    {
      "id": "EPIC-011",
      "name": "Email Integration",
      "phase": "phase-4",
      "priority": "P1",
      "timeline": "Week 14",
      "storyPoints": 34,
      "file": "epics/EPIC-011-email-integration.md"
    },
    {
      "id": "EPIC-012",
      "name": "Calendar Deep Integration",
      "phase": "phase-4",
      "priority": "P1",
      "timeline": "Week 15",
      "storyPoints": 26,
      "file": "epics/EPIC-012-calendar-deep-integration.md"
    },
    {
      "id": "EPIC-013",
      "name": "Communication Integrations",
      "phase": "phase-4",
      "priority": "P1",
      "timeline": "Week 16",
      "storyPoints": 34,
      "file": "epics/EPIC-013-communication-integrations.md"
    },
    {
      "id": "EPIC-014",
      "name": "Autonomous Agent Mode",
      "phase": "phase-5",
      "priority": "P1",
      "timeline": "Weeks 17-18",
      "storyPoints": 34,
      "file": "epics/EPIC-014-autonomous-agent-mode.md"
    },
    {
      "id": "EPIC-015",
      "name": "Conversation Memory",
      "phase": "phase-5",
      "priority": "P1",
      "timeline": "Weeks 18-19",
      "storyPoints": 21,
      "file": "epics/EPIC-015-conversation-memory.md"
    },
    {
      "id": "EPIC-016",
      "name": "Predictive Suggestions",
      "phase": "phase-5",
      "priority": "P2",
      "timeline": "Weeks 19-20",
      "storyPoints": 21,
      "file": "epics/EPIC-016-predictive-suggestions.md"
    },
    {
      "id": "EPIC-017",
      "name": "Mobile App",
      "phase": "phase-6",
      "priority": "P1",
      "timeline": "Weeks 21-22",
      "storyPoints": 55,
      "file": "epics/EPIC-017-mobile-app.md"
    },
    {
      "id": "EPIC-018",
      "name": "Browser Extension",
      "phase": "phase-6",
      "priority": "P1",
      "timeline": "Weeks 22-23",
      "storyPoints": 34,
      "file": "epics/EPIC-018-browser-extension.md"
    },
    {
      "id": "EPIC-019",
      "name": "Voice & Multi-Modal Capture",
      "phase": "phase-6",
      "priority": "P2",
      "timeline": "Weeks 23-24",
      "storyPoints": 21,
      "file": "epics/EPIC-019-voice-multimodal-capture.md"
    },
    {
      "id": "EPIC-020",
      "name": "Responsive Layout & UX Improvements",
      "phase": "phase-0",
      "priority": "P0",
      "timeline": "Weeks 1-3",
      "storyPoints": 34,
      "file": "epics/EPIC-020-responsive-layout-ux.md"
    }
  ],
  "summary": {
    "totalEpics": 20,
    "totalStoryPoints": 585,
    "totalWeeks": 24,
    "phases": 7,
    "priorityBreakdown": {
      "P0": 1,
      "P1": 17,
      "P2": 2
    }
  }
}
